exasol/pytest_backend/__init__.py
exasol/pytest_backend/config.py
exasol/pytest_backend/itde.py
exasol/pytest_backend/parallel_task.py
exasol/pytest_backend/project_short_tag.py
exasol/pytest_backend/py.typed
exasol/pytest_backend/version.py
pytest_exasol_backend-1.2.1.dist-info/METADATA
pytest_exasol_backend-1.2.1.dist-info/WHEEL
pytest_exasol_backend-1.2.1.dist-info/entry_points.txt
pytest_exasol_backend-1.2.1.dist-info/RECORD
