Metadata-Version: 2.3
Name: pytest-exasol-backend
Version: 1.2.1
Summary: 
Author: Mikhail Beck
Author-email: mikhail.beck@exasol.com
Requires-Python: >=3.10,<4.0
Classifier: Programming Language :: Python :: 3
Classifier: Programming Language :: Python :: 3.10
Classifier: Programming Language :: Python :: 3.11
Classifier: Programming Language :: Python :: 3.12
Classifier: Programming Language :: Python :: 3.13
Requires-Dist: exasol-integration-test-docker-environment (>=4.3,<5)
Requires-Dist: exasol-saas-api (>=2.3,<3)
Requires-Dist: pytest (>=7,<9)
